stsci/__init__.py
stsci/tools/__init__.py
stsci/tools/alert.py
stsci/tools/asnutil.py
stsci/tools/basicpar.py
stsci/tools/bitmask.py
stsci/tools/capable.py
stsci/tools/cfgpars.py
stsci/tools/check_files.py
stsci/tools/clipboard_helper.py
stsci/tools/compmixin.py
stsci/tools/configobj.py
stsci/tools/convertgeis.py
stsci/tools/convertlog.py
stsci/tools/convertwaiveredfits.py
stsci/tools/dialog.py
stsci/tools/editpar.py
stsci/tools/eparoption.py
stsci/tools/filedlg.py
stsci/tools/fileutil.py
stsci/tools/fitsdiff.py
stsci/tools/gfit.py
stsci/tools/irafglob.py
stsci/tools/irafglobals.py
stsci/tools/irafutils.py
stsci/tools/iterfile.py
stsci/tools/linefit.py
stsci/tools/listdlg.py
stsci/tools/logutil.py
stsci/tools/minmatch.py
stsci/tools/mputil.py
stsci/tools/nmpfit.py
stsci/tools/parseinput.py
stsci/tools/readgeis.py
stsci/tools/stpyfits.py
stsci/tools/swapgeis.py
stsci/tools/taskpars.py
stsci/tools/teal.py
stsci/tools/teal_bttn.py
stsci/tools/textutil.py
stsci/tools/tkrotext.py
stsci/tools/validate.py
stsci/tools/version.py
stsci/tools/versioninfo.py
stsci/tools/vtor_checks.py
stsci/tools/wcsutil.py
stsci/tools/xyinterp.py
stsci/tools/tests/__init__.py
stsci/tools/tests/test_bitmask.py
stsci/tools/tests/test_breadcrumb.py
stsci/tools/tests/test_cfgobj.py
stsci/tools/tests/test_check_files.py
stsci/tools/tests/test_compmixin.py
stsci/tools/tests/test_irafutils.py
stsci/tools/tests/test_isfits.py
stsci/tools/tests/test_minmatch.py
stsci/tools/tests/test_mputil.py
stsci/tools/tests/test_stpyfits.py
stsci/tools/tests/test_tkrotext.py
stsci/tools/tests/test_xyinterp.py
stsci/tools/tests/data/acs_test.fits
stsci/tools/tests/data/cdva2.fits
stsci/tools/tests/data/cfgobj_output.ref
stsci/tools/tests/data/o4sp040b0_raw.fits
stsci/tools/tests/data/rt_sample.cfg
stsci/tools/tests/data/rt_sample.cfgspc
stsci/tools/tests/data/u40x010hm_c0f.fits
stsci/tools/tests/data/waivered.fits
stsci.tools-4.2.0.dist-info/LICENSE.md
stsci.tools-4.2.0.dist-info/METADATA
stsci.tools-4.2.0.dist-info/WHEEL
stsci.tools-4.2.0.dist-info/entry_points.txt
stsci.tools-4.2.0.dist-info/top_level.txt
stsci.tools-4.2.0.dist-info/RECORD
